{
  "title": "Retinol Anti-Aging Night Cream",
  "slug": "retinol-anti-aging-night-cream",
  "category": "Beauty & Personal Care",
  "image": "https://placehold.co/600x600/14213D/FBF7F0?text=Night%2BCream",
  "price_original": 34.99,
  "price_now": 16.99,
  "discount_percent": 51,
  "affiliate_network": "Amazon Associates",
  "affiliate_url": "https://www.amazon.com/s?k=Retinol+Anti-Aging+Night+Cream&tag=storeforless-21",
  "rating": 4.3,
  "short_description": "Reduces fine lines, hydrating formula.",
  "description": "A hydrating night cream formulated with retinol to help reduce the appearance of fine lines overnight.",
  "featured": false,
  "ships_to": "",
  "date_added": "2026-07-08T00:00:00.000Z"
}